ArabHijiri/__init__.py
ArabHijiri-0.0.5.dist-info/METADATA
ArabHijiri-0.0.5.dist-info/WHEEL
ArabHijiri-0.0.5.dist-info/top_level.txt
ArabHijiri-0.0.5.dist-info/RECORD
