Metadata-Version: 2.1
Name: ArabHijiri
Version: 0.0.5
Summary: Getting the Hijiri (Arabic) date in arabic language and numbers
Home-page: UNKNOWN
Author: Youssef M. Khalil
Author-email: youssefkhalil320@gmail.com
License: UNKNOWN
Keywords: python,date,time,Hijiridate,arabic,arabicdate,islamic
Platform: UNKNOWN
Classifier: Development Status :: 1 - Planning
Classifier: Intended Audience :: Developers
Classifier: Programming Language :: Python :: 3
Classifier: Operating System :: Unix
Classifier: Operating System :: MacOS :: MacOS X
Classifier: Operating System :: Microsoft :: Windows
Requires-Dist: requests
Requires-Dist: datetime
